frontier/__init__.py
frontier/admin.py
frontier/apps.py
frontier/models.py
frontier/tests.py
frontier/utils.py
frontier/views.py
frontier/management/commands/frontier.py
frontier/management/commands/__pycache__/frontier.cpython-38.pyc
frontier/migrations/__init__.py
frontier/presets/Bootstrap.py
frontier/presets/Preset.py
frontier/presets/React.py
frontier/presets/ReactBootstrap.py
frontier/presets/ReactTailwind.py
frontier/presets/Tailwind.py
frontier/presets/Vue.py
frontier/presets/VueBootstrap.py
frontier/presets/VueTailwind.py
frontier/presets/__init__.py
frontier/presets/__pycache__/Bootstrap.cpython-38.pyc
frontier/presets/__pycache__/Preset.cpython-38.pyc
frontier/presets/__pycache__/React.cpython-38.pyc
frontier/presets/__pycache__/ReactBootstrap.cpython-38.pyc
frontier/presets/__pycache__/ReactTailwind.cpython-38.pyc
frontier/presets/__pycache__/Tailwind.cpython-38.pyc
frontier/presets/__pycache__/Vue.cpython-38.pyc
frontier/presets/__pycache__/VueBootstrap.cpython-38.pyc
frontier/presets/__pycache__/VueTailwind.cpython-38.pyc
frontier/presets/__pycache__/__init__.cpython-38.pyc
frontier/presets/samples/bootstrap/src/js/bootstrap.js
frontier/presets/samples/bootstrap/src/js/index.js
frontier/presets/samples/bootstrap/src/scss/_variables.scss
frontier/presets/samples/bootstrap/src/scss/app.scss
frontier/presets/samples/default/package.json
frontier/presets/samples/default/webpack.mix.js
frontier/presets/samples/react/config/.babelrc
frontier/presets/samples/react/src/App.js
frontier/presets/samples/react/src/index.css
frontier/presets/samples/react/src/index.js
frontier/presets/samples/react/src/components/Example.js
frontier/presets/samples/react_bootstrap/src/App.js
frontier/presets/samples/react_bootstrap/src/index.css
frontier/presets/samples/react_bootstrap/src/index.js
frontier/presets/samples/react_bootstrap/src/components/Example.js
frontier/presets/samples/react_tailwind/config/postcss.config.js
django_frontier-0.5.3.dist-info/LICENSE
django_frontier-0.5.3.dist-info/METADATA
django_frontier-0.5.3.dist-info/WHEEL
django_frontier-0.5.3.dist-info/top_level.txt
django_frontier-0.5.3.dist-info/RECORD
